COPYING
MANIFEST.in
README.rst
setup.cfg
setup.py
checkbox_support/__init__.py
checkbox_support/udev.py
checkbox_support.egg-info/PKG-INFO
checkbox_support.egg-info/SOURCES.txt
checkbox_support.egg-info/dependency_links.txt
checkbox_support.egg-info/entry_points.txt
checkbox_support.egg-info/requires.txt
checkbox_support.egg-info/top_level.txt
checkbox_support/contrib/__init__.py
checkbox_support/contrib/xrandr.py
checkbox_support/dbus/__init__.py
checkbox_support/dbus/udisks2.py
checkbox_support/helpers/__init__.py
checkbox_support/helpers/human_readable_bytes.py
checkbox_support/heuristics/__init__.py
checkbox_support/heuristics/udev.py
checkbox_support/heuristics/udisks2.py
checkbox_support/heuristics/tests/__init__.py
checkbox_support/heuristics/tests/test_udisks2.py
checkbox_support/lib/__init__.py
checkbox_support/lib/bit.py
checkbox_support/lib/conversion.py
checkbox_support/lib/dmi.py
checkbox_support/lib/input.py
checkbox_support/lib/path.py
checkbox_support/lib/pci.py
checkbox_support/lib/template.py
checkbox_support/lib/tz.py
checkbox_support/lib/usb.py
checkbox_support/parsers/__init__.py
checkbox_support/parsers/cpuinfo.py
checkbox_support/parsers/cputable
checkbox_support/parsers/cputable.py
checkbox_support/parsers/dkms_info.py
checkbox_support/parsers/dmidecode.py
checkbox_support/parsers/efi.py
checkbox_support/parsers/image_info.py
checkbox_support/parsers/kernel_cmdline.py
checkbox_support/parsers/lshwjson.py
checkbox_support/parsers/meminfo.py
checkbox_support/parsers/modinfo.py
checkbox_support/parsers/modprobe.py
checkbox_support/parsers/pactl.py
checkbox_support/parsers/pci_config.py
checkbox_support/parsers/submission.py
checkbox_support/parsers/udevadm.py
checkbox_support/parsers/xinput.py
checkbox_support/parsers/tests/__init__.py
checkbox_support/parsers/tests/test_cpuinfo.py
checkbox_support/parsers/tests/test_cputable.py
checkbox_support/parsers/tests/test_dkms_info.py
checkbox_support/parsers/tests/test_dmi.py
checkbox_support/parsers/tests/test_dmidecode.py
checkbox_support/parsers/tests/test_efi.py
checkbox_support/parsers/tests/test_image_info.py
checkbox_support/parsers/tests/test_modinfo.py
checkbox_support/parsers/tests/test_modprobe.py
