Metadata-Version: 1.0
Name: checkbox-support
Version: 0.25
Summary: CheckBox support library
Home-page: https://launchpad.net/checkbox/
Author: Sylvain Pineau
Author-email: sylvain.pineau@canonical.com
License: GPLv3
Platform: UNKNOWN
